Metadata-Version: 1.1
Name: citi-wikibot
Version: 0.4.13
Summary: CITI's Wiki page editing for lazy people.
Home-page: https://github.com/citi-ufpe/citi-wikibot
Author: Vanessa Barreiros
Author-email: vanessa.barreiros@citi.org.br
License: UNKNOWN
Keywords: wiki,bot,wikibot,citi
Platform: UNKNOWN
Classifier: License :: OSI Approved :: MIT License
Classifier: Programming Language :: Python
Classifier: Programming Language :: Python :: 3
Classifier: Programming Language :: Python :: 3.6
Classifier: Development Status :: 2 - Pre-Alpha
Classifier: Topic :: Utilities
